vartools/__init__.py
vartools-1.0.1.dist-info/METADATA
vartools-1.0.1.dist-info/WHEEL
vartools-1.0.1.dist-info/licenses/LICENSE
vartools-1.0.1.dist-info/RECORD
