Metadata-Version: 2.4
Name: vartools
Version: 1.0.1
Summary: A Python library for different financial calculations and functions, including Value at Risk (VaR), portfolio optimization, and backtesting.
Project-URL: Homepage, https://github.com/LuisMB09/vartools
Project-URL: Issues, https://github.com/LuisMB09/vartools
Author-email: Luis Márquez <luismaba2004@gmail.com>
Maintainer-email: Luis Márquez <luismaba2004@gmail.com>
License: GPL-3.0-only
License-File: LICENSE
Classifier: License :: OSI Approved :: GNU General Public License v3 (GPLv3)
Classifier: Operating System :: OS Independent
Classifier: Programming Language :: Python :: 3
Requires-Python: >=3.7
Requires-Dist: matplotlib>=3.9.1
Requires-Dist: numpy>=1.26.3
Requires-Dist: pandas>=2.2.2
Requires-Dist: scipy>=1.11.4
Requires-Dist: yfinance>=0.2.54
